setup.py
slackrtm/__init__.py
slackrtm/channel.py
slackrtm/client.py
slackrtm/im.py
slackrtm/server.py
slackrtm/slackrequest.py
slackrtm.egg-info/PKG-INFO
slackrtm.egg-info/SOURCES.txt
slackrtm.egg-info/dependency_links.txt
slackrtm.egg-info/not-zip-safe
slackrtm.egg-info/requires.txt
slackrtm.egg-info/top_level.txt