Metadata-Version: 1.0
Name: slackrtm
Version: 0.2.1
Summary: Python client for Slack.com
Home-page: http://github.com/llimllib/slackrtm
Author: Bill Mill
Author-email: ryan@slack-corp.com
License: MIT
Platform: UNKNOWN
